Metadata-Version: 1.0
Name: Quantum-Game
Version: 0.0.1
Summary: A guessing game built on quantum mechanical theory
Home-page: UNKNOWN
Author: Nataly Nuila
Author-email: <nataly.nuila@gmail.com>
License: UNKNOWN
Platform: UNKNOWN
